{
  "@context": [
    "https://www.w3.org/2019/wot/td/v1",
    "https://www.w3.org/2019/wot/tm"
  ],
  "title": "Product76d376e1",
  "description": "Product76d376e1 by Mfg255a699d",
  "properties": {
    "breakerStatus": {
      "type": "number",
      "description": "The breakerStatus of the device"
    },
    "chargeStatus": {
      "type": "boolean",
      "description": "The chargeStatus of the device"
    },
    "emergencyMode": {
      "type": "string",
      "description": "The emergencyMode of the device"
    },
    "protectionSetpoint": {
      "type": "boolean",
      "description": "The protectionSetpoint of the device"
    }
  },
  "actions": {
    "toggle": {
      "description": "Toggle the device state"
    }
  },
  "events": {
    "alert": {
      "description": "An alert event"
    }
  }
}