{
  "@context": [
    "https://www.w3.org/2019/wot/td/v1",
    "https://www.w3.org/2019/wot/tm"
  ],
  "title": "Product44b874a2",
  "description": "Product44b874a2 by Mfg5b9b525f",
  "properties": {
    "demandResponse": {
      "type": "string",
      "description": "The demandResponse of the device"
    },
    "oilQuality": {
      "type": "object",
      "description": "An object containing nested properties for oilQuality",
      "properties": {
        "dataRate": {
          "type": "string",
          "description": "The dataRate of the nested object"
        }
      }
    },
    "remoteControlCapability": {
      "type": "number",
      "description": "The remoteControlCapability of the device"
    }
  },
  "actions": {
    "toggle": {
      "description": "Toggle the device state"
    }
  },
  "events": {
    "alert": {
      "description": "An alert event"
    }
  }
}